<index xmlns="http://docbook.org/ns/docbook">

<indexdiv>
<title>E</title>

<indexentry>
<primaryie>Entering markup, 14, 18, 22-33</primaryie>
</indexentry>

<indexentry>
<primaryie>eSATA, 56, 58-61</primaryie>
<seealsoie>Serial ATA</seealsoie>
</indexentry>

<indexentry>
<primaryie>evaluating expressions, 44</primaryie>
</indexentry>
</indexdiv>

<indexdiv>
<title>U</title>

<indexentry>
<primaryie>Ubiquitous networking, 34, 44, 173-199</primaryie>
</indexentry>

<indexentry>
<primaryie>Universal Serial Bus, 50-55</primaryie>
</indexentry>

<indexentry>
<primaryie>Up time, 2, 5</primaryie>
</indexentry>

<indexentry>
<primaryie>USB</primaryie>
<seeie>Universal Serial Bus</seeie>
</indexentry>
</indexdiv>
</index>
